{
  "last_updated": "January 17, 2026, 04:29 UTC",
  "categories": {
    "tech_news": [
      {
        "rank": 1,
        "image": "https://images.pushsquare.com/3c36bf1f29bd0/large.jpg",
        "title": "9 PS Plus Extra, Premium Games for January 2026 Announced - Push Square",
        "description": "It takes a Village",
        "source_link": "https://www.pushsquare.com/news/2026/01/9-ps-plus-extra-premium-games-for-january-2026-announced"
      },
      {
        "rank": 2,
        "image": "https://cdn.mos.cms.futurecdn.net/wnPRxaDiXL5QdrAn9Ym2an-1920-80.jpg",
        "title": "\"There are going to be multiple maps coming this year\": Arc Raiders dev teases 2026 roadmap, and maybe some new maps \"even grander than what we've got now\" - GamesRadar+",
        "description": "Embark has big plans for Arc Raiders in 2026",
        "source_link": "https://www.gamesradar.com/games/third-person-shooter/there-are-going-to-be-multiple-maps-coming-this-year-arc-raiders-dev-teases-2026-roadmap-and-maybe-some-new-maps-even-grander-than-what-weve-got-now/"
      },
      {
        "rank": 3,
        "image": "https://platform.theverge.com/wp-content/uploads/sites/2/2025/03/257586_Nvidia_RTX_5070_TWarren_0006.jpg?quality=90&strip=all&crop=0%2C10.471204188482%2C100%2C79.057591623037&w=1200",
        "title": "Asus says it\u2019s dropping the RTX 5070 Ti as the memory shortage squeezes supply - The Verge",
        "description": "Asus is reportedly ending production of its RTX 5070 Ti and 16GB RTX 5060 Ti GPUs due to a lack of supply amidst the ongoing RAM shortage.",
        "source_link": "https://www.theverge.com/news/863000/asus-nvidia-rtx-5070-ti-5060-ti-supply-rumors"
      },
      {
        "rank": 4,
        "image": "https://assets-prd.ignimgs.com/2026/01/15/resident-evil-showcase-january-15-2026-14-29-screenshot-1768516227258.png?width=1280&format=jpg&auto=webp&quality=80",
        "title": "Resident Evil Showcase January 2026: Everything Announced - IGN",
        "description": "Today, Capcom is holding a Resident Evil Showcase event set to feature \"brand new gameplay and news\" for Resident Evil Requiem, among other things.",
        "source_link": "https://www.ign.com/articles/resident-evil-showcase-january-2026-5-things-we-learned"
      },
      {
        "rank": 5,
        "image": "https://images.ctfassets.net/s5n2t79q9icq/6CK0Ulrx3a5dhtVlNjcxrB/5febfad3bd2658bb9d258e75ae5200ea/SLD_Rad_Superdrop_960x540.jpg",
        "title": "Secret Lair: Rad Superdrop - Magic: The Gathering",
        "description": "Equip yourself with a Geiger counter and embrace that neon glow! Secret Lair's Rad Superdrop is bringing retro realness on January 26, 2026.",
        "source_link": "https://magic.wizards.com/en/news/announcements/secret-lair-rad-superdrop"
      },
      {
        "rank": 6,
        "image": "https://kotaku.com/app/uploads/2026/01/image-6-1200x675.jpg",
        "title": "Trump Uses Stardew Valley To Threaten Third Term - Kotaku",
        "description": "The Trump administration keeps using video games to meme its way through fascism",
        "source_link": "https://kotaku.com/donald-trump-white-house-stardew-valley-whole-milk-ai-2000660273"
      },
      {
        "rank": 7,
        "image": "https://images.nintendolife.com/48e4da83f278b/large.jpg",
        "title": "Sonic The Hedgehog Kicks Off 35th Anniversary Celebrations In Style - Nintendo Life",
        "description": "\"Forever fast\"",
        "source_link": "https://www.nintendolife.com/news/2026/01/sonic-the-hedgehog-kicks-off-35th-anniversary-celebrations-in-style"
      },
      {
        "rank": 8,
        "image": "https://www.gamespot.com/a/uploads/screen_kubrick/1179/11799911/4635847-screenshot2026-01-15at2.03.37%E2%80%AFpm.png",
        "title": "Amazon's Big MMO That Started Strong Is Shutting Down - GameSpot",
        "description": "It's the end of the road for this title.",
        "source_link": "https://www.gamespot.com/articles/amazons-big-mmo-that-started-strong-is-shutting-down/1100-6537436/"
      },
      {
        "rank": 9,
        "image": "https://i0.wp.com/9to5google.com/wp-content/uploads/sites/4/2025/06/Android-16-logo-2.jpg?resize=1200%2C628&quality=82&strip=all&ssl=1",
        "title": "Android 16 QPR3 adds \u2018Screen automation\u2019 on Pixel 10 for \u2018computer use\u2019 - 9to5Google",
        "description": "At the moment, Gemini\u2019s \u201cComputer Use\u201d efforts are focused on desktop web as seen by the Gemini Agent available for...",
        "source_link": "http://9to5google.com/2026/01/15/android-16-qpr3-screen-automation/"
      },
      {
        "rank": 10,
        "image": "https://assetsio.gnwcdn.com/Screenshot-2026-01-15-at-18.39.39.png?width=1200&height=630&fit=crop&enable=upscale&auto=webp",
        "title": "Sony removes hundreds of \"shovelware\" games from its digital storefront originating from one developer - GamesIndustry.biz",
        "description": "Sony has reportedly removed hundreds of ThiGames games from its PlayStation Store.",
        "source_link": "https://www.gamesindustry.biz/sony-removes-hundreds-of-shovelware-games-from-its-digital-storefront"
      }
    ],
    "trending_movies": [
      {
        "rank": 1,
        "image": "https://image.tmdb.org/t/p/w200/p4bW2sJKAwcHuLpfoZK7Zo63osA.jpg",
        "title": "The Rip",
        "description": "Trust frays when a team of Miami cops discovers millions in cash inside a run-down stash house, calling everyone \u2014 and everything \u2014 into question....",
        "source_link": "https://www.themoviedb.org/movie/1306368"
      },
      {
        "rank": 2,
        "image": "https://image.tmdb.org/t/p/w200/xC6zdIoIHjhOIFmjNyGgtzhuhiF.jpg",
        "title": "Killer Whale",
        "description": "A gripping survival thriller centred around best friends, Trish Stevens and Maddie Clark, who find themselves locked into a deadly face-off against th...",
        "source_link": "https://www.themoviedb.org/movie/1412598"
      },
      {
        "rank": 3,
        "image": "https://image.tmdb.org/t/p/w200/A5lswNlytTUrnMWsuD0NFfhZlf3.jpg",
        "title": "Rental Family",
        "description": "An American actor in Tokyo struggles to find purpose until he lands an unusual gig: working for a Japanese 'rental family' agency, playing stand-in ro...",
        "source_link": "https://www.themoviedb.org/movie/1208348"
      },
      {
        "rank": 4,
        "image": "https://image.tmdb.org/t/p/w200/vobigFZFvbYPf6ElYJu07P9rH8C.jpg",
        "title": "Dust Bunny",
        "description": "Ten-year-old Aurora asks her hitman neighbor to kill the monster under her bed that she claims ate her family. To protect her, he must battle an onsla...",
        "source_link": "https://www.themoviedb.org/movie/1043197"
      },
      {
        "rank": 5,
        "image": "https://image.tmdb.org/t/p/w200/xeEw3eLeSFmJgXZzmF2Efww0q3s.jpg",
        "title": "xXx",
        "description": "Xander Cage is your standard adrenaline junkie with no fear and a lousy attitude. When the US Government \"recruits\" him to go on a mission, he's not e...",
        "source_link": "https://www.themoviedb.org/movie/7451"
      },
      {
        "rank": 6,
        "image": "https://image.tmdb.org/t/p/w200/kK1BGkG3KAvWB0WMV1DfOx9yTMZ.jpg",
        "title": "28 Years Later: The Bone Temple",
        "description": "Dr. Kelson finds himself in a shocking new relationship - with consequences that could change the world as they know it - and Spike's encounter with J...",
        "source_link": "https://www.themoviedb.org/movie/1272837"
      },
      {
        "rank": 7,
        "image": "https://image.tmdb.org/t/p/w200/lE9KpVwgeWHMwgwkNaeH5nEFh20.jpg",
        "title": "Avatar: Fire and Ash",
        "description": "In the wake of the devastating war against the RDA and the loss of their eldest son, Jake Sully and Neytiri face a new threat on Pandora: the Ash Peop...",
        "source_link": "https://www.themoviedb.org/movie/83533"
      },
      {
        "rank": 8,
        "image": "https://image.tmdb.org/t/p/w200/erTRAi241eYF4K8KoGGOI8kFPox.jpg",
        "title": "Predator: Badlands",
        "description": "Cast out from his clan, a young Predator finds an unlikely ally in a damaged android and embarks on a treacherous journey in search of the ultimate ad...",
        "source_link": "https://www.themoviedb.org/movie/1242898"
      },
      {
        "rank": 9,
        "image": "https://image.tmdb.org/t/p/w200/cWsBscZzwu5brg9YjNkGewRUvJX.jpg",
        "title": "The Housemaid",
        "description": "Trying to escape her past, Millie Calloway accepts a job as a live-in housemaid for the wealthy Nina and Andrew Winchester. But what begins as a dream...",
        "source_link": "https://www.themoviedb.org/movie/1368166"
      },
      {
        "rank": 10,
        "image": "https://image.tmdb.org/t/p/w200/firAhZA0uQvRL2slp7v3AnOj0ZX.jpg",
        "title": "Marty Supreme",
        "description": "In 1950s New York, table tennis player Marty Mauser, a young man with a dream no one respects, goes to Hell and back in pursuit of greatness....",
        "source_link": "https://www.themoviedb.org/movie/1317288"
      }
    ]
  }
}